rustbam-0.2.0.dist-info/METADATA
rustbam-0.2.0.dist-info/WHEEL
rustbam-0.2.0.dist-info/entry_points.txt
rustbam-0.2.0.dist-info/licenses/LICENSE
rustbam.libs/libbz2-b8fe8c25.so.1
rustbam/cli.py
rustbam/__init__.py
rustbam/_rustbam.abi3.so
rustbam-0.2.0.dist-info/RECORD
