Metadata-Version: 2.4
Name: rustbam
Version: 0.2.0
Classifier: Programming Language :: Python
Classifier: Programming Language :: Rust
Classifier: Topic :: Scientific/Engineering :: Bio-Informatics
License-File: LICENSE
Summary: A Rust-based BAM depth calculator for Python.
Keywords: bam,bioinformatics,genomics,rust,parallel
Author-email: Seongmin Choi <soymintc@gmail.com>
License: MIT
Requires-Python: >=3.8
